makeblock/__init__.py
makeblock/boards/__init__.py
makeblock/boards/base/__init__.py
makeblock/boards/codey/__init__.py
makeblock/boards/codey/modules.py
makeblock/boards/cyberpi/__init__.py
makeblock/boards/halocode/__init__.py
makeblock/boards/mbuild/__init__.py
makeblock/boards/mcore/__init__.py
makeblock/boards/meauriga/__init__.py
makeblock/boards/megapi/__init__.py
makeblock/boards/megapipro/__init__.py
makeblock/boards/meorion/__init__.py
makeblock/boards/neuron/__init__.py
makeblock/boards/neuron/modules.py
makeblock/boards/rj25n/__init__.py
makeblock/comm/SerialPort/__init__.py
makeblock/comm/SerialPort/test.py
makeblock/comm/mlink/__init__.py
makeblock/ext/__init__.py
makeblock/ext/piano/__init__.py
makeblock/modules/cyberpi/__init__.py
makeblock/modules/cyberpi/api_cyberpi_api.py
makeblock/modules/cyberpi/modules.py
makeblock/modules/cyberpi/table_cyberpi_api.py
makeblock/modules/halocode/__init__.py
makeblock/modules/halocode/modules.py
makeblock/modules/mbuild/__init__.py
makeblock/modules/mbuild/modules.py
makeblock/modules/neuron/__init__.py
makeblock/modules/rj25/__init__.py
makeblock/modules/rj25/modules.py
makeblock/modules/rj25n/__init__.py
makeblock/modules/rj25n/modules.py
makeblock/protocols/PackData.py
makeblock/protocols/Protocols.py
makeblock/protocols/__init__.py
makeblock/utils/__init__.py
makeblock-0.1.7.dist-info/METADATA
makeblock-0.1.7.dist-info/WHEEL
makeblock-0.1.7.dist-info/top_level.txt
makeblock-0.1.7.dist-info/RECORD
